nbpreprocessor/__init__.py
nbpreprocessor/_nbdev.py
nbpreprocessor/core.py
nbpreprocessor-0.0.1.dist-info/LICENSE
nbpreprocessor-0.0.1.dist-info/METADATA
nbpreprocessor-0.0.1.dist-info/WHEEL
nbpreprocessor-0.0.1.dist-info/entry_points.txt
nbpreprocessor-0.0.1.dist-info/top_level.txt
nbpreprocessor-0.0.1.dist-info/RECORD
